Workbook

Sheet Main
A1: Date of Creation: | B1: 45863
A2: Last Updated: | B2: 46012
C5: Incomes | D5: =D10 -> 4785714.3 | G5: Outcomes | H5: =SUM(K8:K16) -> 989257.14
G7: Expense | H7: Unit Cost | I7: Times/Month | J7: Total Cost | K7: After Benefits | L7: Pay Date (day)
G8: Kung Fu | H8: 250000 | I8: 1 | J8: =H8*I8 -> 250000 | K8: =Tabla1[[#This Row],[Total Cost]] -> 250000 | L8: 5
C9: Income | D9: Unit Cost | E9: Pay Date | G9: Transport | H9: 3550 | I9: 24 | J9: =H9*I9 -> 85200 | K9: =J9 -> 85200 | L9: =A1048575+_xlfn.CEILING.MATH((TODAY()-A1048575)/21, 1)*21 -> 46174
C10: Salary | D10: 4785714.3 | E10: 25 | G10: Didi | H10: 6400 | I10: =2*4 -> 8 | J10: =H10*I10 -> 51200 | K10: =J10 -> 51200 | L10: Per service
C11: Wellbeing Lifestyle | D11: =35*D26 -> 125000 | E11: 2-3 days after request | G11: Hair salon | H11: 20000 | I11: 1 | J11: =H11*I11 -> 20000 | K11: =J11 -> 20000 | L11: 23
C12: Remaining | D12: =35*D27 -> 0 | E12: - | G12: Pensión | H12: =$D$10*0.04 -> 191428.57 | I12: 1 | J12: =H12*I12 -> 191428.57 | K12: =J12 -> 191428.57 | L12: 25
C13: Pluxee | D13: 440000 | E13: 10 | G13: Salud | H13: =$D$10*0.04 -> 191428.57 | I13: 1 | J13: =H13*I13 -> 191428.57 | K13: =J13 -> 191428.57 | L13: 25
C14: Remaining | D14: =D13-Tabla1[[#This Row],[Total Cost]]-J15 -> 197500 | E14: - | G14: Rent | H14: 200000 | I14: 1 | J14: =H14*I14 -> 200000 | K14: =J14 -> 200000 | L14: 25
G15: Creatine (monthly) | H15: 170000 | I15: 0.25 | J15: =H15*I15 -> 42500 | K15: 0 | L15: 5 servings left
G16: Protein | H16: 205000 | I16: 1 | J16: =H16*I16 -> 205000 | K16: =0 -> 0 | L16: 5 servings left
C18: NET | D18: =D5-H5 -> 3796457.1 | G18: Amount to Cash Out (monthly) | H18: =_xlfn.CEILING.MATH(SUM(K8,K10,K11,K14)/10000)*10000 -> 530000
C20: ="Savings on " & TEXT(B2, "tt.MM.jjjj") -> Savings on 21.12.2025 | D20: 39534683
C21: (Calculations per last recorded savings)
C25: EUR | D25: =1/'COP'!B46 -> 4166.6667
C26: USD | D26: =1/'COP'!B150 -> 3571.4286
D29: Goal | E29: Time till Germany (from 05.08.2025) [months] | F29: Expected Date
C30: Funds for 1 Year | D30: =12000*D25 -> 50000000 | E30: =_xlfn.CEILING.MATH((D30-$D$20-$D$5+'Another Expenses'!G2)/$D$18) -> 5 | F30: =EDATE(DATE(YEAR($B$2), MONTH($B$2), $E$10),E30) -> 46167
C31: Funds for 2 Years | D31: =24000*D25 -> 100000000 | E31: =_xlfn.CEILING.MATH((D31-$D$20-$D$5+'Another Expenses'!G3)/$D$18) -> 15 | F31: =EDATE(DATE(YEAR($B$2), MONTH($B$2), $E$10),E31) -> 46471
A1048575: 46048

Sheet Another Expenses
C2: AWS - CLF-02 | D2: =100*Main!D26 -> 357142.86 | F2: Total Expenses | G2: =SUM(D2:D28) -> 9758285.7
C3: DELF B2 | D3: 490000
C4: GOETHE C1 | D4: 1788000
C5: Kung Fu - Maestro Chang | D5: =100*Main!D26 -> 357142.86
C6: Guitarra Módulo PC | D6: 500000
C7: Gaming PC | D7: 4500000
C8: Kung Fu - December Promotion | D8: 100000
C9: Bed | D9: =650000+730000-500000 -> 880000
C10: Regalo Saris | D10: 200000
C11: Secondary Phone | D11: 262000
C12: Mobile Plan | D12: 204000
C13: Kung Fu Hoodie | D13: 120000
C14: AWS - SAA-C02

Sheet Debt
B3: TOTAL | C3: =SUM(D8:D28)+SUM(H8:H28) -> 15664180
C6: Mamá | G6: Investment
C7: Name | D7: Amount | E7: Notes | G7: Name | H7: Amount | I7: Notes
C8: Carro | D8: =316170-300000 -> 16170 | E8: -Chaqueta (300k) | G8: CDT Finandina | H8: 10211610 | I8: Cash out on 3.2.2026
C9: Cama | D9: =500000-(730000+200000)+600000 -> 170000
C10: CDT (March 1st) | D10: 5200000
C11: HiperMarFish | E11: -100000
C12: Camarón Grande Precocido | D12: 48000
C13: 2 Lomito de Róbalo 500g | D13: 18400

Sheet COP
A1: Name | B1: Value
A2: COP | B2: 1
A3: AED | B3: 0.001029
A4: AFN | B4: 0.017946
A5: ALL | B5: 0.022862
A6: AMD | B6: 0.104117
A7: ANG | B7: 0.000502
A8: AOA | B8: 0.257843
A9: ARS | B9: 0.388953
A10: AUD | B10: 0.000392
A11: AWG | B11: 0.000502
A12: AZN | B12: 0.000476
A13: BAM | B13: 0.000469
... A167: ZWL | B167: 0.00708
