Workbook
Name ChartAmounts: OFFSET(Tracker!$D$5,MATCH(EOMONTH(TODAY(),-6)+1,Tracker!$B$6:$B$65,1),0,7,1)
Name ChartDates: OFFSET(Tracker!$B$5,MATCH(EOMONTH(TODAY(),-6)+1,Tracker!$B$6:$B$65,1),0,7,1)

Sheet Main
A1: Date of Creation: | B1: 45863
A2: Last Updated: | B2: 46012
C5: Monthly Incomes | D5: =SUM(D8:D10) -> 5533706.5 | G5: Monthly Outcomes | H5: =SUM(K8:K18) -> 1135168.6
C7: Income | D7: Unit Cost | E7: Pay Date | G7: Expense | H7: Unit Cost | I7: Times/Month | J7: Total Cost | K7: After Benefits | L7: Pay Date (day) | M7: Additional Information
C8: Salary | D8: =71254500/14 -> 5089607.1 | E8: 25 | G8: Kung Fu | H8: 250000 | I8: 1 | J8: =H8*I8 -> 250000 | K8: =Tabla1[[#This Row],[Total Cost]] -> 250000 | L8: 5 | M8: -
C9: CDT Finandina | D9: =241890.11/3 -> 80630.037 | E9: The 2nd every 3 months | G9: SITP | H9: 3550 | I9: 16 | J9: =H9*I9 -> 56800 | K9: =J9 -> 56800 | L9: =A1048575+_xlfn.CEILING.MATH((TODAY()-A1048575)/21, 1)*21 -> 46321 | M9: -
C10: CDT Banco Santander | D10: =1090408/3 -> 363469.33 | E10: The 16nd every 3 months | G10: Laptop Drive | H10: 15000 | I10: 8 | J10: =H10*I10 -> 120000 | K10: =Tabla1[[#This Row],[Total Cost]] -> 120000
C11: Wellbeing Lifestyle | D11: =35*D29 -> 111821.09 | E11: 2-3 days after request | G11: Didi Bike | H11: 6400 | I11: =2*4 -> 8 | J11: =H11*I11 -> 51200 | K11: =J11 -> 51200 | L11: Per service | M11: -
C12: Remaining | D12: =35*D30 -> 0 | E12: - | G12: Hair salon | H12: 20000 | I12: 1 | J12: =H12*I12 -> 20000 | K12: =J12 -> 20000 | L12: 23 | M12: -
C13: Pluxee | D13: 440000 | E13: 10 | G13: Pensión | H13: =$D$8*0.04 -> 203584.29 | I13: 1 | J13: =H13*I13 -> 203584.29 | K13: =J13 -> 203584.29 | L13: 25 | M13: -
C14: Monthly Remaining | D14: =D13-J17-J18 -> 338676.47 | E14: - | G14: Salud | H14: =$D$8*0.04 -> 203584.29 | I14: 1 | J14: =H14*I14 -> 203584.29 | K14: =J14 -> 203584.29 | L14: 25 | M14: -
G15: Rent | H15: 200000 | I15: 1 | J15: =H15*I15 -> 200000 | K15: =J15 -> 200000 | L15: 25 | M15: -
G16: Liquidity | H16: 30000 | I16: 1 | J16: =H16*I16 -> 30000 | K16: =Tabla1[[#This Row],[Total Cost]] -> 30000
G17: Creatine (monthly) | H17: 170000 | I17: 0.25 | J17: =H17*I17 -> 42500 | K17: 0 | L17: 5 servings left | M17: Look 'My Stats'>Supplements
G18: Protein | H18: 250000 | I18: =1/4.25 -> 0.23529412 | J18: =H18*I18 -> 58823.529 | K18: =0 -> 0 | L18: 5 servings left | M18: Look 'My Stats'>Supplements
C21: Monthly NET | D21: =D5-H5 -> 4398537.9
C23: ="Savings on " & TEXT(B2, "dd.MM.yyyy") -> Savings on 21.12.2025 | D23: 39534683 | G23: Amount to Cash Out (monthly) | H23: =_xlfn.CEILING.MATH(SUM(K8,K12,K15)/10000)*10000 -> 470000
C24: (Calculations per last recorded savings)
J25: =SUM(J9:J11) -> 228000
C28: EUR | D28: =1/'COP Rates'!B46 -> 3703.7037
C29: USD | D29: =1/'COP Rates'!B150 -> 3194.8882
D32: Goal | E32: Time till Germany (from 05.08.2025) [months] | F32: Expected Date
C33: Funds for 1 Year | D33: =12000*D28 -> 44444444 | E33: =_xlfn.CEILING.MATH((D33-$D$23-$D$5+'Another Expenses'!G2)/$D$21) -> 3 | F33: =EDATE(DATE(YEAR($B$2), MONTH($B$2), $E$8),E33) -> 46106
C34: Funds for 2 Years | D34: =24000*D28 -> 88888889 | E34: =_xlfn.CEILING.MATH((D34-$D$23-$D$5+'Another Expenses'!G3)/$D$21) -> 10 | F34: =EDATE(DATE(YEAR($B$2), MONTH($B$2), $E$8),E34) -> 46320
A1048575: 46048

Sheet Tracker
B2: Amount for Investment | C2: 50000000
B5: Date | C5: General Balance | D5: Account Balance | E5: Gain/Loss | F5: Difference from Expected Net | H5: General Balance Scope
B6: 46023 | C6: =27037512.04+15400000 -> 42437512 | D6: =27037512.04 -> 27037512 | E6: N/A | F6: N/A | H6: Date | I6: General Balance
B7: =EDATE(B6,1) -> 46054 | C7: =30821932.81+15400000 -> 46221933 | D7: =30821932.81 -> 30821933 | E7: =Table9[[#This Row],[General Balance]]-C6 -> 3784420.8 | F7: =4520137.94-E7 -> 735717.17 | H7: =INDEX(Table9[Date],MATCH(EOMONTH(TODAY(),-6)+1,Table9[Date],1)) -> 46143 | I7: =INDEX(Table9[General Balance],MATCH(EOMONTH(TODAY(),-6)+1,Table9[Date],1)) -> 55912013
B8: =EDATE(B7,1) -> 46082 | C8: =34124040.84+15400000 -> 49524041 | D8: =34124040.84 -> 34124041 | E8: =Table9[[#This Row],[General Balance]]-C7 -> 3302108 | F8: =4520137.94-E8 -> 1218029.9 | H8: =INDEX(Table9[Date],MATCH(EOMONTH(TODAY(),-5)+1,Table9[Date],1)) -> 46174 | I8: =INDEX(Table9[General Balance],MATCH(EOMONTH(TODAY(),-5)+1,Table9[Date],1)) -> 61491092
B9: =EDATE(B8,1) -> 46113 | C9: =37390636.8+15400000 -> 52790637 | D9: =37390636.8 -> 37390637 | E9: =Table9[[#This Row],[General Balance]]-C8 -> 3266596 | F9: =4520137.94-E9 -> 1253542 | H9: =INDEX(Table9[Date],MATCH(EOMONTH(TODAY(),-4)+1,Table9[Date],1)) -> 46204 | I9: =INDEX(Table9[General Balance],MATCH(EOMONTH(TODAY(),-4)+1,Table9[Date],1)) -> 64900000
B10: =EDATE(B9,1) -> 46143 | C10: =40512013.15+15400000 -> 55912013 | D10: =40512013.15 -> 40512013 | E10: =Table9[[#This Row],[General Balance]]-C9 -> 3121376.4 | F10: =4520137.94-E10 -> 1398761.6 | H10: =INDEX(Table9[Date],MATCH(EOMONTH(TODAY(),-3)+1,Table9[Date],1)) -> 46235 | I10: =INDEX(Table9[General Balance],MATCH(EOMONTH(TODAY(),-3)+1,Table9[Date],1)) -> 65265422
B11: =EDATE(B10,1) -> 46174 | C11: =46091091.96+15400000 -> 61491092 | D11: =46091091.96 -> 46091092 | E11: =Table9[[#This Row],[General Balance]]-C10 -> 5579078.8 | F11: =4520137.94-E11 -> -1058940.9 | H11: =INDEX(Table9[Date],MATCH(EOMONTH(TODAY(),-2)+1,Table9[Date],1)) -> 46266 | I11: =INDEX(Table9[General Balance],MATCH(EOMONTH(TODAY(),-2)+1,Table9[Date],1)) -> 69506977
B12: =EDATE(B11,1) -> 46204 | C12: =9500000+15400000+37000000+3000000 -> 64900000 | D12: =9500000 -> 9500000 | E12: =Table9[[#This Row],[General Balance]]-C11 -> 3408908 | F12: =4520137.94-E12 -> 1111229.9 | H12: =INDEX(Table9[Date],MATCH(EOMONTH(TODAY(),-1)+1,Table9[Date],1)) -> 46296 | I12: =INDEX(Table9[General Balance],MATCH(EOMONTH(TODAY(),-1)+1,Table9[Date],1)) -> 74189384
B13: =EDATE(B12,1) -> 46235 | C13: =Table9[[#This Row],[Account Balance]]+15400000+37000000+6000000 -> 65265422 | D13: 6865421.5 | E13: =4682407-350000-220000-57030-16500-160000-469769 -> 3409108 | F13: =4520137.94-E13 -> 1111029.9
B14: =EDATE(B13,1) -> 46266 | C14: =C13+(Table9[[#This Row],[Account Balance]]-D13)+Main!D10+Main!D9 -> 69506977 | D14: 10662877 | E14: =Table9[[#This Row],[General Balance]]-C13 -> 4241555 | F14: =Main!D21-E14 -> 156982.91 | H14: Difference from Expected Net Scope
B15: =EDATE(B14,1) -> 46296 | C15: =C14+4682407 -> 74189384 | D15: 25255077 | E15: =Table9[[#This Row],[General Balance]]-C14 -> 4682407 | F15: =4520137.94-E15 -> -162269.06 | H15: Date | I15: Difference from Expected Net
B16: =EDATE(B15,1) -> 46327 | C16: - | D16: - | E16: =Table9[[#This Row],[General Balance]]-C15 -> #VALUE! | F16: =4520137.94-E16 -> #VALUE! | H16: =INDEX(Table9[Date],MATCH(EOMONTH(TODAY(),-6)+1,Table9[Date],1)) -> 46143 | I16: =INDEX(Table9[Difference from Expected Net],MATCH(EOMONTH(TODAY(),-6)+1,Table9[Date],1)) -> 1398761.6
B17: =EDATE(B16,1) -> 46357 | C17: - | D17: - | E17: =Table9[[#This Row],[General Balance]]-C16 -> #VALUE! | F17: =4520137.94-E17 -> #VALUE! | H17: =INDEX(Table9[Date],MATCH(EOMONTH(TODAY(),-5)+1,Table9[Date],1)) -> 46174 | I17: =INDEX(Table9[Difference from Expected Net],MATCH(EOMONTH(TODAY(),-5)+1,Table9[Date],1)) -> -1058940.9
B18: =EDATE(B17,1) -> 46388 | C18: - | D18: - | E18: =Table9[[#This Row],[General Balance]]-C17 -> #VALUE! | F18: =4520137.94-E18 -> #VALUE! | H18: =INDEX(Table9[Date],MATCH(EOMONTH(TODAY(),-4)+1,Table9[Date],1)) -> 46204 | I18: =INDEX(Table9[Difference from Expected Net],MATCH(EOMONTH(TODAY(),-4)+1,Table9[Date],1)) -> 1111229.9
B19: =EDATE(B18,1) -> 46419 | C19: - | D19: - | E19: =Table9[[#This Row],[General Balance]]-C18 -> #VALUE! | F19: =4520137.94-E19 -> #VALUE! | H19: =INDEX(Table9[Date],MATCH(EOMONTH(TODAY(),-3)+1,Table9[Date],1)) -> 46235 | I19: =INDEX(Table9[Difference from Expected Net],MATCH(EOMONTH(TODAY(),-3)+1,Table9[Date],1)) -> 1111029.9
B20: =EDATE(B19,1) -> 46447 | C20: - | D20: - | E20: =Table9[[#This Row],[General Balance]]-C19 -> #VALUE! | F20: =4520137.94-E20 -> #VALUE! | H20: =INDEX(Table9[Date],MATCH(EOMONTH(TODAY(),-2)+1,Table9[Date],1)) -> 46266 | I20: =INDEX(Table9[Difference from Expected Net],MATCH(EOMONTH(TODAY(),-2)+1,Table9[Date],1)) -> 156982.91
B21: =EDATE(B20,1) -> 46478 | C21: - | D21: - | E21: =Table9[[#This Row],[General Balance]]-C20 -> #VALUE! | F21: =4520137.94-E21 -> #VALUE! | H21: =INDEX(Table9[Date],MATCH(EOMONTH(TODAY(),-1)+1,Table9[Date],1)) -> 46296 | I21: =INDEX(Table9[Difference from Expected Net],MATCH(EOMONTH(TODAY(),-1)+1,Table9[Date],1)) -> -162269.06
B22: =EDATE(B21,1) -> 46508 | C22: - | D22: - | E22: =Table9[[#This Row],[General Balance]]-C21 -> #VALUE! | F22: =4520137.94-E22 -> #VALUE!
B23: =EDATE(B22,1) -> 46539 | C23: - | D23: - | E23: =Table9[[#This Row],[General Balance]]-C22 -> #VALUE! | F23: =4520137.94-E23 -> #VALUE!
B24: =EDATE(B23,1) -> 46569 | C24: - | D24: - | E24: =Table9[[#This Row],[General Balance]]-C23 -> #VALUE! | F24: =4520137.94-E24 -> #VALUE!
B25: =EDATE(B24,1) -> 46600 | C25: - | D25: - | E25: =Table9[[#This Row],[General Balance]]-C24 -> #VALUE! | F25: =4520137.94-E25 -> #VALUE!
B26: =EDATE(B25,1) -> 46631 | C26: - | D26: - | E26: =Table9[[#This Row],[General Balance]]-C25 -> #VALUE! | F26: =4520137.94-E26 -> #VALUE!
B27: =EDATE(B26,1) -> 46661 | C27: - | D27: - | E27: =Table9[[#This Row],[General Balance]]-C26 -> #VALUE! | F27: =4520137.94-E27 -> #VALUE!
B28: =EDATE(B27,1) -> 46692 | C28: - | D28: - | E28: =Table9[[#This Row],[General Balance]]-C27 -> #VALUE! | F28: =4520137.94-E28 -> #VALUE!
B29: =EDATE(B28,1) -> 46722 | C29: - | D29: - | E29: =Table9[[#This Row],[General Balance]]-C28 -> #VALUE! | F29: =4520137.94-E29 -> #VALUE!
B30: =EDATE(B29,1) -> 46753 | C30: - | D30: - | E30: =Table9[[#This Row],[General Balance]]-C29 -> #VALUE! | F30: =4520137.94-E30 -> #VALUE!
B31: =EDATE(B30,1) -> 46784 | C31: - | D31: - | E31: =Table9[[#This Row],[General Balance]]-C30 -> #VALUE! | F31: =4520137.94-E31 -> #VALUE!
B32: =EDATE(B31,1) -> 46813 | C32: - | D32: - | E32: =Table9[[#This Row],[General Balance]]-C31 -> #VALUE! | F32: =4520137.94-E32 -> #VALUE!
B33: =EDATE(B32,1) -> 46844 | C33: - | D33: - | E33: =Table9[[#This Row],[General Balance]]-C32 -> #VALUE! | F33: =4520137.94-E33 -> #VALUE!
... B65: =EDATE(B64,1) -> 47818 | C65: - | D65: - | E65: =Table9[[#This Row],[General Balance]]-C64 -> #VALUE! | F65: =4520137.94-E65 -> #VALUE!

Sheet Another Expenses
C2: AWS - CLF-02 | D2: =100*Main!D29 -> 319488.82 | F2: Total Expenses | G2: =SUM(D2:D29) -> 12031800
C3: DELF B2 | D3: 490000
C4: GOETHE C1 | D4: 1788000
C5: Kung Fu - Maestro Chang | D5: =100*Main!D29 -> 319488.82
C6: Guitarra Módulo PC | D6: 234220
C7: Pedido Temu | D7: 14602
C8: Gaming PC | D8: 4500000
C9: Kung Fu - December Promotion | D9: 100000
C10: Bed | D10: =650000+730000-500000 -> 880000
C11: Regalo Saris | D11: 200000
C12: Secondary Phone | D12: 262000
C13: Mobile Plan | D13: 204000
C14: Kung Fu Hoodie | D14: 120000
C15: AWS - SAA-C02 | D15: -
C16: Kung Fu - June Promotion | D16: 100000
C17: Odontología | D17: 900000
C18: Chaqueta Velez | D18: 1000000
C19: Viaje Cali | D19: 600000

Sheet Debt
B3: TOTAL | C3: =D28+I28 -> 52631380
C6: Mamá | H6: Investment
C7: Description | D7: Incoming | E7: Outcoming | F7: Notes | H7: Name | I7: Amount | J7: Notes
C8: Carro | D8: =316170 -> 316170 | H8: CDT Finandina | I8: 10211610 | J8: Cash out on 2.9.2026
C9: Cama | D9: =500000-(730000+200000)+600000 -> 170000 | H9: CDT Banco Santander | I9: 37000000 | J9: Cash out on 17.01.2027
C10: CDT (March 1st) | D10: 5400000
C11: Chaqueta | E11: 300000
C12: HiperMarFish | E12: 100000
C13: Camarón Grande Precocido | E13: 48000
C14: 2 Lomito de Róbalo 500g | E14: 18400
C28: Summary | D28: =SUM(Table5[Incoming])-SUM(Table5[Outcoming]) -> 5419770 | H28: Summary | I28: =SUM(Table6[Amount]) -> 47211610

Sheet Portfolio
E8: Condition | F8: Action | G8: % Adjusted
E9: USD/COP < 3.000 | F9: Reallocate 5% from CDTs to USD | G9: USD 20%, CDTs 39%
E10: USD/COP > 3.600 | F10: Hold | G10: No Changes
E11: EUR/COP < 3.300 | F11: Reallocate 10% from CDTs to EUR | G11: EUR 40%, CDTs 34%
E12: EUR/COP > 3.700 | F12: Hold | G12: No Changes
E13: USD & EUR Decrease | F13: Increase EUR | G13: EUR 40%, USD 20%, CDTs 29%
E14: EUR/COP >3800 (90 days)* | F14: Unlock EUR portion | G14: EUR = 30%
E16: Investment Type | F16: Percentage | G16: Current Amount | H16: Notes
E17: EUR* | F17: 0.3 | G17: =Tracker!$C$2*Portfolio!F17 -> 15000000 | H17: Current: 0% until hitting EUR limit
E18: USD | F18: 0.15 | G18: 6000000 | H18: Current: 3.000.000,00. Transfer Pending
E19: Liquidity | F19: 0.1 | G19: 6000000
E20: CDTs | F20: 0.44 | G20: =Tracker!$C$2*Portfolio!F20 -> 22000000 | H20: Current: 74% until hitting EUR limit
E21: Stocks | F21: =1-SUM(F17:F20) -> 0.01 | G21: =Tracker!$C$2*Portfolio!F21 -> 500000 | H21: Pending
E23: Date Bought | F23: Date Sold | G23: Asset | H23: Units | I23: Price Buy | J23: Price Sell | K23: Total Invested (COP) | L23: Total Value | M23: Gain/Loss (COP) | N23: % Return | O23: Notes
E24: 46219 | F24: - | G24: USD | H24: 926.69817 | I24: 3237.3 | J24: - | K24: 3000000 | L24: - | M24: =Table10[[#This Row],[Total Value]]-Table10[[#This Row],[Total Invested (COP)]] -> #VALUE! | N24: =Table10[[#This Row],[Gain/Loss (COP)]]*100/Table10[[#This Row],[Total Invested (COP)]] -> #VALUE!
E25: 46225 | F25: - | G25: USD | H25: 933.47 | I25: 3213.78 | J25: - | K25: 3000000 | L25: - | M25: =Table10[[#This Row],[Total Value]]-Table10[[#This Row],[Total Invested (COP)]] -> #VALUE! | N25: =Table10[[#This Row],[Gain/Loss (COP)]]*100/Table10[[#This Row],[Total Invested (COP)]] -> #VALUE!
E26: - | F26: 46226 | G26: USD | H26: 100 | I26: 3237.3 | J26: 3257.13 | K26: =H26*I26 -> 323730 | L26: =H26*J26 -> 325713 | M26: =Table10[[#This Row],[Total Value]]-Table10[[#This Row],[Total Invested (COP)]] -> 1983 | N26: =Table10[[#This Row],[Gain/Loss (COP)]]*100/Table10[[#This Row],[Total Invested (COP)]] -> 0.61254749
E27: - | F27: - | G27: EUR | H27: - | I27: - | J27: - | K27: - | L27: - | M27: =Table10[[#This Row],[Total Value]]-Table10[[#This Row],[Total Invested (COP)]] -> #VALUE! | N27: =Table10[[#This Row],[Gain/Loss (COP)]]*100/Table10[[#This Row],[Total Invested (COP)]] -> #VALUE!
E28: - | F28: - | G28: AAPL | H28: - | I28: - | J28: - | K28: - | L28: - | M28: =Table10[[#This Row],[Total Value]]-Table10[[#This Row],[Total Invested (COP)]] -> #VALUE! | N28: =Table10[[#This Row],[Gain/Loss (COP)]]*100/Table10[[#This Row],[Total Invested (COP)]] -> #VALUE!
E29: - | F29: - | G29: MSTF | H29: - | I29: - | J29: - | K29: - | L29: - | M29: =Table10[[#This Row],[Total Value]]-Table10[[#This Row],[Total Invested (COP)]] -> #VALUE! | N29: =Table10[[#This Row],[Gain/Loss (COP)]]*100/Table10[[#This Row],[Total Invested (COP)]] -> #VALUE!
E30: - | F30: - | G30: V | H30: - | I30: - | J30: - | K30: - | L30: - | M30: =Table10[[#This Row],[Total Value]]-Table10[[#This Row],[Total Invested (COP)]] -> #VALUE! | N30: =Table10[[#This Row],[Gain/Loss (COP)]]*100/Table10[[#This Row],[Total Invested (COP)]] -> #VALUE!
E31: - | F31: - | G31: JNJ | H31: - | I31: - | J31: - | K31: - | L31: - | M31: =Table10[[#This Row],[Total Value]]-Table10[[#This Row],[Total Invested (COP)]] -> #VALUE! | N31: =Table10[[#This Row],[Gain/Loss (COP)]]*100/Table10[[#This Row],[Total Invested (COP)]] -> #VALUE!
E32: - | F32: - | G32: KO | H32: - | I32: - | J32: - | K32: - | L32: - | M32: =Table10[[#This Row],[Total Value]]-Table10[[#This Row],[Total Invested (COP)]] -> #VALUE! | N32: =Table10[[#This Row],[Gain/Loss (COP)]]*100/Table10[[#This Row],[Total Invested (COP)]] -> #VALUE!

Sheet COP Rates
A1: Name | B1: Value
A2: COP | B2: 1
A3: AED | B3: 0.00115
A4: AFN | B4: 0.020409
A5: ALL | B5: 0.02495
A6: AMD | B6: 0.114057
A7: ANG | B7: 0.000561
A8: AOA | B8: 0.287895
A9: ARS | B9: 0.472868
A10: AUD | B10: 0.000437
A11: AWG | B11: 0.000561
A12: AZN | B12: 0.000536
A13: BAM | B13: 0.000528
... A167: ZWL | B167: 0.008354
